nice_figures/__init__.py
nice_figures/add_border.py
nice_figures/add_numbering.py
nice_figures/load_cols.py
nice_figures/load_style.py
nice_figures/version.py
nice_figures/data/cols.json
nice_figures-0.0.2.dist-info/LICENSE
nice_figures-0.0.2.dist-info/METADATA
nice_figures-0.0.2.dist-info/WHEEL
nice_figures-0.0.2.dist-info/top_level.txt
nice_figures-0.0.2.dist-info/RECORD
