Metadata-Version: 2.1
Name: nice-figures
Version: 0.0.2
Summary: Methods and style files for making publication quality figures
Home-page: https://github.com/Rob217/nice-figures
Author: Rob Bettles
Author-email: rjbcoding@gmail.com
License: UNKNOWN
Platform: UNKNOWN
Classifier: Programming Language :: Python :: 3
Classifier: License :: OSI Approved :: MIT License
Classifier: Operating System :: OS Independent
Requires-Python: >=3.6
Requires-Dist: matplotlib
Requires-Dist: numpy
